Metadata-Version: 2.1
Name: python-PCF8574
Version: 1.0.0
Summary:  TI's PCF8574 python driver 
Home-page: https://github.com/goutamkumar77/python-PCF8574
Author: Goutam Kumar
Author-email: goutam1000@gmail.com
License: MIT
Keywords: PCF8574
Platform: UNKNOWN
Classifier: Development Status :: 5 - Production/Stable
Classifier: Intended Audience :: Education
Classifier: Operating System :: Other OS
Classifier: Topic :: System :: Hardware :: Hardware Drivers
Classifier: License :: OSI Approved :: MIT License
Classifier: Programming Language :: Python :: 3
